pydantic_basedtyping/__init__.py
pydantic_basedtyping/__main__.py
pydantic_basedtyping-0.1.0.dist-info/METADATA
pydantic_basedtyping-0.1.0.dist-info/WHEEL
pydantic_basedtyping-0.1.0.dist-info/entry_points.txt
pydantic_basedtyping-0.1.0.dist-info/RECORD
