Metadata-Version: 2.3
Name: pydantic-basedtyping
Version: 0.1.0
Summary: todo
Author-email: KotlinIsland <kotlinisland@users.noreply.github.com>
License: MIT
Requires-Python: >=3.9
Requires-Dist: basedtyping>=0.1.5
Requires-Dist: pydantic<3,>=2.4.2
